{
  "_note1": "KEEP THIS FILE! Check it into a version control system (VCS) like git.",
  "_note2": "ObjectBox manages crucial IDs for your object model. See docs for details.",
  "_note3": "If you have VCS merge conflicts, you must resolve them according to ObjectBox docs.",
  "entities": [
    {
      "id": "1:2288211406474458435",
      "lastPropertyId": "3:6339256854418474128",
      "name": "Animal",
      "properties": [
        {
          "id": "1:3350162259144883294",
          "name": "id",
          "type": 6,
          "flags": 1
        },
        {
          "id": "2:2714618977300964646",
          "name": "tag",
          "type": 9
        },
        {
          "id": "3:6339256854418474128",
          "name": "done",
          "type": 1
        }
      ],
      "relations": []
    }
  ],
  "lastEntityId": "1:2288211406474458435",
  "lastIndexId": "0:0",
  "lastRelationId": "0:0",
  "lastSequenceId": "0:0",
  "modelVersion": 5,
  "modelVersionParserMinimum": 5,
  "retiredEntityUids": [],
  "retiredIndexUids": [],
  "retiredPropertyUids": [],
  "retiredRelationUids": [],
  "version": 1
}